pyfunge
setup.py
PyFunge.egg-info/PKG-INFO
PyFunge.egg-info/SOURCES.txt
PyFunge.egg-info/dependency_links.txt
PyFunge.egg-info/not-zip-safe
PyFunge.egg-info/top_level.txt
funge/__init__.py
funge/exception.py
funge/fingerprint.py
funge/ip.py
funge/main.py
funge/platform.py
funge/program.py
funge/semantics.py
funge/space.py
funge/stack.py
funge/vector.py
funge/fp/__init__.py
funge/fp/fp_3DSP.py
funge/fp/fp_BASE.py
funge/fp/fp_BOOL.py
funge/fp/fp_CPLI.py
funge/fp/fp_DATE.py
funge/fp/fp_DIRF.py
funge/fp/fp_EVAR.py
funge/fp/fp_FILE.py
funge/fp/fp_FIXP.py
funge/fp/fp_FPDP.py
funge/fp/fp_FPRT.py
funge/fp/fp_FPSP.py
funge/fp/fp_FRTH.py
funge/fp/fp_HRTI.py
funge/fp/fp_ICAL.py
funge/fp/fp_IIPC.py
funge/fp/fp_IMAP.py
funge/fp/fp_IMTH.py
funge/fp/fp_INDV.py
funge/fp/fp_JSTR.py
funge/fp/fp_LONG.py
funge/fp/fp_MODE.py
funge/fp/fp_MODU.py
funge/fp/fp_NCRS.py
funge/fp/fp_NULL.py
funge/fp/fp_ORTH.py
funge/fp/fp_PERL.py
funge/fp/fp_REFC.py
funge/fp/fp_ROMA.py
funge/fp/fp_SCKE.py
funge/fp/fp_SETS.py
funge/fp/fp_SOCK.py
funge/fp/fp_STRN.py
funge/fp/fp_SUBR.py
funge/fp/fp_TERM.py
funge/fp/fp_TIME.py
funge/fp/fp_TOYS.py
funge/languages/__init__.py
funge/languages/befunge93.py
funge/languages/funge98.py
funge/languages/funge98opt.py