Metadata-Version: 1.0
Name: PyFunge
Version: 0.5-rc2
Summary: Functional, compliant and optimizing Funge-98 implementation
Home-page: http://mearie.org/projects/pyfunge/
Author: Kang Seonghoon
Author-email: public+pyfunge@mearie.org
License: MIT
Platform: UNKNOWN
Classifier: Development Status :: 3 - Alpha
Classifier: Environment :: Console
Classifier: Intended Audience :: Developers
Classifier: License :: OSI Approved :: MIT License
Classifier: Operating System :: OS Independent
Classifier: Programming Language :: Other
Classifier: Topic :: Software Development :: Interpreters
